micro_sqlalchemy_ext/__init__.py
micro_sqlalchemy_ext-1.0.0.dist-info/METADATA
micro_sqlalchemy_ext-1.0.0.dist-info/WHEEL
micro_sqlalchemy_ext-1.0.0.dist-info/top_level.txt
micro_sqlalchemy_ext-1.0.0.dist-info/RECORD
